spongepy/cleaner.py
spongepy/cli.py
spongepy/config_loader.py
spongepy/utils.py
spongepy-0.1.2.dist-info/entry_points.txt
spongepy-0.1.2.dist-info/METADATA
spongepy-0.1.2.dist-info/WHEEL
spongepy-0.1.2.dist-info/RECORD
